suitcase/specfile/__init__.py
suitcase/specfile/_version.py
suitcase/specfile/tests/__init__.py
suitcase/specfile/tests/conftest.py
suitcase/specfile/tests/tests.py
suitcase/specfile/tests/data_from_suitcase_v0.7.0/count_1.spec
suitcase/specfile/tests/data_from_suitcase_v0.7.0/count_3.spec
suitcase/specfile/tests/data_from_suitcase_v0.7.0/rel_scan.spec
suitcase/specfile/tests/data_from_suitcase_v0.7.0/scan.spec
suitcase/specfile/tests/documents/count_1.jsonl
suitcase/specfile/tests/documents/count_3.jsonl
suitcase/specfile/tests/documents/rel_scan.jsonl
suitcase/specfile/tests/documents/scan.jsonl
suitcase_specfile-0.2.5.dist-info/LICENSE
suitcase_specfile-0.2.5.dist-info/METADATA
suitcase_specfile-0.2.5.dist-info/WHEEL
suitcase_specfile-0.2.5.dist-info/entry_points.txt
suitcase_specfile-0.2.5.dist-info/top_level.txt
suitcase_specfile-0.2.5.dist-info/RECORD
