Metadata-Version: 2.1
Name: suitcase-specfile
Version: 0.2.5
Summary: UNKNOWN
Home-page: UNKNOWN
License: BSD (3-clause)
Platform: UNKNOWN
Classifier: Development Status :: 2 - Pre-Alpha
Classifier: Natural Language :: English
Classifier: Programming Language :: Python :: 3.6
License-File: LICENSE
Requires-Dist: event-model (>=1.8.0)
Requires-Dist: jinja2
Requires-Dist: suitcase-utils (>=0.5.0)
